{
	"vertices": [
		{
			"id": "a",
			
			
			"gameBoardTile": {
				"xLocation": "0.0",
				"yLocation": "0.0",
				"tileMovementType": "GameBoardContinueTile",
				"gameBoardTileType": "Start"
			}
		},
		{
			"id": "b",
			
			
			"gameBoardTile": {
				"xLocation": "0.0",
				"yLocation": "0.0",
				"tileMovementType": "GameBoardContinueTile",
				"gameBoardTileType": "Start"
			}
		},		
		{
			"id": "c",
			
			
			"gameBoardTile": {
				"xLocation": "0.0",
				"yLocation": "0.0",
				"tileMovementType": "GameBoardContinueTile",
				"gameBoardTileType": "Payday"
			}
		},		
		{
			"id": "d",
			
			
			"gameBoardTile": {
				"xLocation": "0.0",
				"yLocation": "0.0",
				"tileMovementType": "GameBoardContinueTile",
				"gameBoardTileType": "Action"
			}
		},		
		{
			"id": "e",
			
			
			"gameBoardTile": {
				"xLocation": "0.0",
				"yLocation": "0.0",
				"tileMovementType": "GameBoardContinueTile",
				"gameBoardTileType": "Action"
			}
		},
		{
			"id": "f",
			
			
			"gameBoardTile": {
				"xLocation": "0.0",
				"yLocation": "0.0",
				"tileMovementType": "GameBoardContinueTile",
				"gameBoardTileType": "Start"
			}
		},
		{
			"id": "g",
			
			
			"gameBoardTile": {
				"xLocation": "0.0",
				"yLocation": "0.0",
				"tileMovementType": "GameBoardContinueTile",
				"gameBoardTileType": "Action"
			}
		},
		{
			"id": "h",
			
			
			"gameBoardTile": {
				"xLocation": "0.0",
				"yLocation": "0.0",
				"tileMovementType": "GameBoardContinueTile",
				"gameBoardTileType": "Action"
			}
		},
		{
			"id": "i",
			
			
			"gameBoardTile": {
				"xLocation": "0.0",
				"yLocation": "0.0",
				"tileMovementType": "GameBoardContinueTile",
				"gameBoardTileType": "Action"
			}
		},
		{
			"id": "j",
			
			
			"gameBoardTile": {
				"xLocation": "0.0",
				"yLocation": "0.0",
				"tileMovementType": "GameBoardContinueTile",
				"gameBoardTileType": "Action"
			}
		},
		{
			"id": "k",
			
			
			"gameBoardTile": {
				"xLocation": "0.0",
				"yLocation": "0.0",
				"tileMovementType": "GameBoardContinueTile",
				"gameBoardTileType": "Action"
			}
		},
		{
			"id": "l",
			
			
			"gameBoardTile": {
				"xLocation": "0.0",
				"yLocation": "0.0",
				"tileMovementType": "GameBoardContinueTile",
				"gameBoardTileType": "Action"
			}
		},
		{
			"id": "m",
			
			
			"gameBoardTile": {
				"xLocation": "0.0",
				"yLocation": "0.0",
				"tileMovementType": "GameBoardContinueTile",
				"gameBoardTileType": "Action"
			}
		},
		{
			"id": "n",
			
			
			"gameBoardTile": {
				"xLocation": "0.0",
				"yLocation": "0.0",
				"tileMovementType": "GameBoardContinueTile",
				"gameBoardTileType": "Action"
			}
		},
		{
			"id": "o",
			
			
			"gameBoardTile": {
				"xLocation": "0.0",
				"yLocation": "0.0",
				"tileMovementType": "GameBoardContinueTile",
				"gameBoardTileType": "Action"
			}
		},
		{
			"id": "p",
			
			
			"gameBoardTile": {
				"xLocation": "0.0",
				"yLocation": "0.0",
				"tileMovementType": "GameBoardStopTile",
				"gameBoardTileType": "Stop",
				"gameBoardStopTileType": "Graduation"
			}
		},
		{
			"id": "q",
			
			
			"gameBoardTile": {
				"xLocation": "0.0",
				"yLocation": "0.0",
				"tileMovementType": "GameBoardContinueTile",
				"gameBoardTileType": "Action"
			}
		},
		{
			"id": "r",
			
			
			"gameBoardTile": {
				"xLocation": "0.0",
				"yLocation": "0.0",
				"tileMovementType": "GameBoardContinueTile",
				"gameBoardTileType": "Action"
			}
		},
		{
			"id": "s",
			
			
			"gameBoardTile": {
				"xLocation": "0.0",
				"yLocation": "0.0",
				"tileMovementType": "GameBoardContinueTile",
				"gameBoardTileType": "Action"
			}
		},
		{
			"id": "t",
			
			
			"gameBoardTile": {
				"xLocation": "0.0",
				"yLocation": "0.0",
				"tileMovementType": "GameBoardContinueTile",
				"gameBoardTileType": "Action"
			}
		},
		{
			"id": "u",
			
			
			"gameBoardTile": {
				"xLocation": "0.0",
				"yLocation": "0.0",
				"tileMovementType": "GameBoardContinueTile",
				"gameBoardTileType": "Payday"
			}
		},
		{
			"id": "v",
			
			
			"gameBoardTile": {
				"xLocation": "0.0",
				"yLocation": "0.0",
				"tileMovementType": "GameBoardContinueTile",
				"gameBoardTileType": "Holiday"
			}
		},
		{
			"id": "w",
			
			
			"gameBoardTile": {
				"xLocation": "0.0",
				"yLocation": "0.0",
				"tileMovementType": "GameBoardContinueTile",
				"gameBoardTileType": "SpinToWin"
			}
		},
		{
			"id": "x",
			
			
			"gameBoardTile": {
				"xLocation": "0.0",
				"yLocation": "0.0",
				"tileMovementType": "GameBoardContinueTile",
				"gameBoardTileType": "Action"
			}
		},
		{
			"id": "y",
			
			
			"gameBoardTile": {
				"xLocation": "0.0",
				"yLocation": "0.0",
				"tileMovementType": "GameBoardContinueTile",
				"gameBoardTileType": "Action"
			}
		},
		{
			"id": "z",
			
			
			"gameBoardTile": {
				"xLocation": "0.0",
				"yLocation": "0.0",
				"tileMovementType": "GameBoardContinueTile",
				"gameBoardTileType": "Payday"
			}
		},
		{
			"id": "aa",
			
			
			"gameBoardTile": {
				"xLocation": "0.0",
				"yLocation": "0.0",
				"tileMovementType": "GameBoardContinueTile",
				"gameBoardTileType": "Action"
			}
		},
		{
        "id": "ab",
        
			
			"gameBoardTile": {
				"xLocation": "0.0",
				"yLocation": "0.0",
            "tileMovementType": "GameBoardStopTile",
            "gameBoardTileType": "Stop",
            "gameBoardStopTileType": "GetMarried"
          }
        },
        {
          "id": "ac",
          
			
			"gameBoardTile": {
				"xLocation": "0.0",
				"yLocation": "0.0",
            "tileMovementType": "GameBoardContinueTile",
			"gameBoardTileType": "Action"
          }
        },
		{
		  "id": "ad",
		  
			
			"gameBoardTile": {
				"xLocation": "0.0",
				"yLocation": "0.0",
		    "tileMovementType": "GameBoardContinueTile",
		    "gameBoardTileType": "Action"
		  }
		},
		{
		  "id": "ae",
		  
			
			"gameBoardTile": {
				"xLocation": "0.0",
				"yLocation": "0.0",
		    "tileMovementType": "GameBoardContinueTile",
		    "gameBoardTileType": "Holiday"
		  }
		},
		{
		  "id": "af",
		  
			
			"gameBoardTile": {
				"xLocation": "0.0",
				"yLocation": "0.0",
		    "tileMovementType": "GameBoardContinueTile",
		    "gameBoardTileType": "Action"
		  }
		},
		{
		  "id": "ag",
		  
			
			"gameBoardTile": {
				"xLocation": "0.0",
				"yLocation": "0.0",
		    "tileMovementType": "GameBoardContinueTile",
		    "gameBoardTileType": "Action"
		  }
		},
		{
		  "id": "ah",
		  
			
			"gameBoardTile": {
				"xLocation": "0.0",
				"yLocation": "0.0",
		    "tileMovementType": "GameBoardContinueTile",
		    "gameBoardTileType": "Payday"
		  }
		},
		{
		  "id": "ai",
		  
			
			"gameBoardTile": {
				"xLocation": "0.0",
				"yLocation": "0.0",
		    "tileMovementType": "GameBoardContinueTile",
		    "gameBoardTileType": "Action"
		  }
		},
		{
		  "id": "aj",
		  
			
			"gameBoardTile": {
				"xLocation": "0.0",
				"yLocation": "0.0",
		    "tileMovementType": "GameBoardContinueTile",
		    "gameBoardTileType": "SpinToWin"
		  }
		},
		{
		  "id": "ak",
		  
			
			"gameBoardTile": {
				"xLocation": "0.0",
				"yLocation": "0.0",
		    "tileMovementType": "GameBoardContinueTile",
		    "gameBoardTileType": "Action"
		  }
		},
		{
		  "id": "al",
		  
			
			"gameBoardTile": {
				"xLocation": "0.0",
				"yLocation": "0.0",
		    "tileMovementType": "GameBoardContinueTile",
		    "gameBoardTileType": "House"
		  }
		},
		{
		  "id": "am",
		  
			
			"gameBoardTile": {
				"xLocation": "0.0",
				"yLocation": "0.0",
		    "tileMovementType": "GameBoardContinueTile",
		    "gameBoardTileType": "Action"
		  }
		},
		{
		  "id": "an",
		  
			
			"gameBoardTile": {
				"xLocation": "0.0",
				"yLocation": "0.0",
		    "tileMovementType": "GameBoardStopTile",
		    "gameBoardTileType": "Stop",
			"gameBoardStopTileType": "NightSchool"
		  }
		},
		{
		  "id": "ao",
		  
			
			"gameBoardTile": {
				"xLocation": "0.0",
				"yLocation": "0.0",
		    "tileMovementType": "GameBoardContinueTile",
		    "gameBoardTileType": "Action"
		  }
		},
		{
		  "id": "ap",
		  
			
			"gameBoardTile": {
				"xLocation": "0.0",
				"yLocation": "0.0",
		    "tileMovementType": "GameBoardContinueTile",
		    "gameBoardTileType": "Action"
		  }
		},
		{
		  "id": "aq",
		  
			
			"gameBoardTile": {
				"xLocation": "0.0",
				"yLocation": "0.0",
		    "tileMovementType": "GameBoardContinueTile",
		    "gameBoardTileType": "Holiday"
		  }
		},
		{
		  "id": "ar",
		  
			
			"gameBoardTile": {
				"xLocation": "0.0",
				"yLocation": "0.0",
		    "tileMovementType": "GameBoardContinueTile",
		    "gameBoardTileType": "Action"
		  }
		},
		{
		  "id": "as",
		  
			
			"gameBoardTile": {
				"xLocation": "0.0",
				"yLocation": "0.0",
		    "tileMovementType": "GameBoardContinueTile",
		    "gameBoardTileType": "Payday"
		  }
		},
		{
		  "id": "at",
		  
			
			"gameBoardTile": {
				"xLocation": "0.0",
				"yLocation": "0.0",
		    "tileMovementType": "GameBoardContinueTile",
		    "gameBoardTileType": "Action"
		  }
		},
		{
		  "id": "au",
		  
			
			"gameBoardTile": {
				"xLocation": "0.0",
				"yLocation": "0.0",
		    "tileMovementType": "GameBoardContinueTile",
		    "gameBoardTileType": "Action"
		  }
		},
		{
		  "id": "av",
		  
			
			"gameBoardTile": {
				"xLocation": "0.0",
				"yLocation": "0.0",
		    "tileMovementType": "GameBoardContinueTile",
		    "gameBoardTileType": "Action"
		  }
		},
		{
		  "id": "aw",
		  
			
			"gameBoardTile": {
				"xLocation": "0.0",
				"yLocation": "0.0",
		    "tileMovementType": "GameBoardContinueTile",
		    "gameBoardTileType": "Action"
		  }
		},
		{
		  "id": "ax",
		  
			
			"gameBoardTile": {
				"xLocation": "0.0",
				"yLocation": "0.0",
		    "tileMovementType": "GameBoardContinueTile",
		    "gameBoardTileType": "Action"
		  }
		},
		{
		  "id": "ay",
		  
			
			"gameBoardTile": {
				"xLocation": "0.0",
				"yLocation": "0.0",
		    "tileMovementType": "GameBoardContinueTile",
		    "gameBoardTileType": "Action"
		  }
		},
		{
		  "id": "az",
		  
			
			"gameBoardTile": {
				"xLocation": "0.0",
				"yLocation": "0.0",
		    "tileMovementType": "GameBoardContinueTile",
		    "gameBoardTileType": "Action"
		  }
		},
		{
		  "id": "aaa",
		  
			
			"gameBoardTile": {
				"xLocation": "0.0",
				"yLocation": "0.0",
		    "tileMovementType": "GameBoardContinueTile",
		    "gameBoardTileType": "Payday"
		  }
		},
		{
		  "id": "aab",
		  
			
			"gameBoardTile": {
				"xLocation": "0.0",
				"yLocation": "0.0",
		    "tileMovementType": "GameBoardContinueTile",
		    "gameBoardTileType": "Action"
		  }
		},
		{
		  "id": "aac",
		  
			
			"gameBoardTile": {
				"xLocation": "0.0",
				"yLocation": "0.0",
		    "tileMovementType": "GameBoardContinueTile",
		    "gameBoardTileType": "Action"
		  }
		},
		{
		  "id": "aad",
		  
			
			"gameBoardTile": {
				"xLocation": "0.0",
				"yLocation": "0.0",
		    "tileMovementType": "GameBoardContinueTile",
		    "gameBoardTileType": "Action"
		  }
		},
		{
		  "id": "aae",
		  
			
			"gameBoardTile": {
				"xLocation": "0.0",
				"yLocation": "0.0",
		    "tileMovementType": "GameBoardContinueTile",
		    "gameBoardTileType": "Action"
		  }
		},
		{
		  "id": "aaf",
		  
			
			"gameBoardTile": {
				"xLocation": "0.0",
				"yLocation": "0.0",
		    "tileMovementType": "GameBoardContinueTile",
		    "gameBoardTileType": "House"
		  }
		},
		{
		  "id": "aag",
		  
			
			"gameBoardTile": {
				"xLocation": "0.0",
				"yLocation": "0.0",
		    "tileMovementType": "GameBoardContinueTile",
		    "gameBoardTileType": "Action"
		  }
		},
		{
		  "id": "aah",
		  
			
			"gameBoardTile": {
				"xLocation": "0.0",
				"yLocation": "0.0",
		    "tileMovementType": "GameBoardContinueTile",
		    "gameBoardTileType": "Payday"
		  }
		},
		{
		  "id": "aai",
		  
			
			"gameBoardTile": {
				"xLocation": "0.0",
				"yLocation": "0.0",
		    "tileMovementType": "GameBoardContinueTile",
		    "gameBoardTileType": "Twins"
		  }
		},
		{
		  "id": "aaj",
		  
			
			"gameBoardTile": {
				"xLocation": "0.0",
				"yLocation": "0.0",
		    "tileMovementType": "GameBoardContinueTile",
		    "gameBoardTileType": "Action"
		  }
		},
		{
		  "id": "aak",
		  
			
			"gameBoardTile": {
				"xLocation": "0.0",
				"yLocation": "0.0",
		    "tileMovementType": "GameBoardContinueTile",
		    "gameBoardTileType": "SpinToWin"
		  }
		},
		{
		  "id": "aal",
		  
			
			"gameBoardTile": {
				"xLocation": "0.0",
				"yLocation": "0.0",
		    "tileMovementType": "GameBoardContinueTile",
		    "gameBoardTileType": "Holiday"
		  }
		},
		{
		  "id": "aam",
		  
			
			"gameBoardTile": {
				"xLocation": "0.0",
				"yLocation": "0.0",
		    "tileMovementType": "GameBoardContinueTile",
		    "gameBoardTileType": "Action"
		  }
		},
		{
		  "id": "aan",
		  
			
			"gameBoardTile": {
				"xLocation": "0.0",
				"yLocation": "0.0",
		    "tileMovementType": "GameBoardContinueTile",
		    "gameBoardTileType": "House"
		  }
		},
		{
		  "id": "aao",
		  
			
			"gameBoardTile": {
				"xLocation": "0.0",
				"yLocation": "0.0",
		    "tileMovementType": "GameBoardContinueTile",
		    "gameBoardTileType": "Payday"
		  }
		},
		{
		  "id": "aap",
		  
			
			"gameBoardTile": {
				"xLocation": "0.0",
				"yLocation": "0.0",
		    "tileMovementType": "GameBoardContinueTile",
		    "gameBoardTileType": "Action"
		  }
		},
		{
		  "id": "aaq",
		  
			
			"gameBoardTile": {
				"xLocation": "0.0",
				"yLocation": "0.0",
		    "tileMovementType": "GameBoardStopTile",
		    "gameBoardTileType": "Stop",
			"gameBoardStopTileType": "Family"
		  }
		},
		{
		  "id": "aar",
		  
			
			"gameBoardTile": {
				"xLocation": "0.0",
				"yLocation": "0.0",
		    "tileMovementType": "GameBoardContinueTile",
		    "gameBoardTileType": "Action"
		  }
		},
		{
		  "id": "aas",
		  
			
			"gameBoardTile": {
				"xLocation": "0.0",
				"yLocation": "0.0",
		    "tileMovementType": "GameBoardContinueTile",
		    "gameBoardTileType": "Holiday"
		  }
		},
		{
		  "id": "aat",
		  
			
			"gameBoardTile": {
				"xLocation": "0.0",
				"yLocation": "0.0",
		    "tileMovementType": "GameBoardContinueTile",
		    "gameBoardTileType": "Action"
		  }
		},
		{
		  "id": "aau",
		  
			
			"gameBoardTile": {
				"xLocation": "0.0",
				"yLocation": "0.0",
		    "tileMovementType": "GameBoardContinueTile",
		    "gameBoardTileType": "Action"
		  }
		},
		{
		  "id": "aav",
		  
			
			"gameBoardTile": {
				"xLocation": "0.0",
				"yLocation": "0.0",
		    "tileMovementType": "GameBoardContinueTile",
		    "gameBoardTileType": "Action"
		  }
		},
		{
		  "id": "aaw",
		  
			
			"gameBoardTile": {
				"xLocation": "0.0",
				"yLocation": "0.0",
		    "tileMovementType": "GameBoardContinueTile",
		    "gameBoardTileType": "Payday"
		  }
		},
		{
		  "id": "aax",
		  
			
			"gameBoardTile": {
				"xLocation": "0.0",
				"yLocation": "0.0",
		    "tileMovementType": "GameBoardContinueTile",
		    "gameBoardTileType": "Action"
		  }
		},
		{
		  "id": "aay",
		  
			
			"gameBoardTile": {
				"xLocation": "0.0",
				"yLocation": "0.0",
		    "tileMovementType": "GameBoardStopTile",
		    "gameBoardTileType": "Stop",
			"gameBoardStopTileType": "Baby"
		  }
		},
		{
		  "id": "aaz",
		  
			
			"gameBoardTile": {
				"xLocation": "0.0",
				"yLocation": "0.0",
		    "tileMovementType": "GameBoardContinueTile",
		    "gameBoardTileType": "Action"
		  }
		},
		{
		  "id": "aaaa",
		  
			
			"gameBoardTile": {
				"xLocation": "0.0",
				"yLocation": "0.0",
		    "tileMovementType": "GameBoardContinueTile",
		    "gameBoardTileType": "Twins"
		  }
		},
		{
		  "id": "aaab",
		  
			
			"gameBoardTile": {
				"xLocation": "0.0",
				"yLocation": "0.0",
		    "tileMovementType": "GameBoardContinueTile",
		    "gameBoardTileType": "House"
		  }
		},
		{
		  "id": "aaac",
		  
			
			"gameBoardTile": {
				"xLocation": "0.0",
				"yLocation": "0.0",
		    "tileMovementType": "GameBoardContinueTile",
		    "gameBoardTileType": "Baby"
		  }
		},
		{
		  "id": "aaad",
		  
			
			"gameBoardTile": {
				"xLocation": "0.0",
				"yLocation": "0.0",
		    "tileMovementType": "GameBoardContinueTile",
		    "gameBoardTileType": "Twins"
		  }
		},
		{
		  "id": "aaae",
		  
			
			"gameBoardTile": {
				"xLocation": "0.0",
				"yLocation": "0.0",
		    "tileMovementType": "GameBoardContinueTile",
		    "gameBoardTileType": "Holiday"
		  }
		},
		{
		  "id": "aaaf",
		  
			
			"gameBoardTile": {
				"xLocation": "0.0",
				"yLocation": "0.0",
		    "tileMovementType": "GameBoardContinueTile",
		    "gameBoardTileType": "Baby"
		  }
		},
		{
		  "id": "aaag",
		  
			
			"gameBoardTile": {
				"xLocation": "0.0",
				"yLocation": "0.0",
		    "tileMovementType": "GameBoardContinueTile",
		    "gameBoardTileType": "Baby"
		  }
		},
		{
		  "id": "aaah",
		  
			
			"gameBoardTile": {
				"xLocation": "0.0",
				"yLocation": "0.0",
		    "tileMovementType": "GameBoardContinueTile",
		    "gameBoardTileType": "Action"
		  }
		},
		{
		  "id": "aaai",
		  
			
			"gameBoardTile": {
				"xLocation": "0.0",
				"yLocation": "0.0",
		    "tileMovementType": "GameBoardContinueTile",
		    "gameBoardTileType": "SpinToWin"
		  }
		},
		{
		  "id": "aaaj",
		  
			
			"gameBoardTile": {
				"xLocation": "0.0",
				"yLocation": "0.0",
		    "tileMovementType": "GameBoardContinueTile",
		    "gameBoardTileType": "Action"
		  }
		},
		{
		  "id": "aaak",
		  
			
			"gameBoardTile": {
				"xLocation": "0.0",
				"yLocation": "0.0",
		    "tileMovementType": "GameBoardContinueTile",
		    "gameBoardTileType": "Action"
		  }
		},
		{
		  "id": "aaal",
		  
			
			"gameBoardTile": {
				"xLocation": "0.0",
				"yLocation": "0.0",
		    "tileMovementType": "GameBoardContinueTile",
		    "gameBoardTileType": "Baby"
		  }
		},
		{
		  "id": "aaam",
		  
			
			"gameBoardTile": {
				"xLocation": "0.0",
				"yLocation": "0.0",
		    "tileMovementType": "GameBoardContinueTile",
		    "gameBoardTileType": "Action"
		  }
		},
		{
		  "id": "aaan",
		  
			
			"gameBoardTile": {
				"xLocation": "0.0",
				"yLocation": "0.0",
		    "tileMovementType": "GameBoardContinueTile",
		    "gameBoardTileType": "House"
		  }
		},
		{
		  "id": "aaao",
		  
			
			"gameBoardTile": {
				"xLocation": "0.0",
				"yLocation": "0.0",
		    "tileMovementType": "GameBoardContinueTile",
		    "gameBoardTileType": "Payday"
		  }
		},
		{
		  "id": "aaap",
		  
			
			"gameBoardTile": {
				"xLocation": "0.0",
				"yLocation": "0.0",
		    "tileMovementType": "GameBoardContinueTile",
		    "gameBoardTileType": "Baby"
		  }
		},
		{
		  "id": "aaaq",
		  
			
			"gameBoardTile": {
				"xLocation": "0.0",
				"yLocation": "0.0",
		    "tileMovementType": "GameBoardStopTile",
		    "gameBoardTileType": "Stop",
			"gameBoardStopTileType": "Holiday"
		  }
		},
		{
		  "id": "aaar",
		  
			
			"gameBoardTile": {
				"xLocation": "0.0",
				"yLocation": "0.0",
		    "tileMovementType": "GameBoardContinueTile",
		    "gameBoardTileType": "Action"
		  }
		},
		{
		  "id": "aaas",
		  
			
			"gameBoardTile": {
				"xLocation": "0.0",
				"yLocation": "0.0",
		    "tileMovementType": "GameBoardContinueTile",
		    "gameBoardTileType": "SpinToWin"
		  }
		},
		{
		  "id": "aaat",
		  
			
			"gameBoardTile": {
				"xLocation": "0.0",
				"yLocation": "0.0",
		    "tileMovementType": "GameBoardContinueTile",
		    "gameBoardTileType": "Action"
		  }
		},
		{
		  "id": "aaau",
		  
			
			"gameBoardTile": {
				"xLocation": "0.0",
				"yLocation": "0.0",
		    "tileMovementType": "GameBoardContinueTile",
		    "gameBoardTileType": "Action"
		  }
		},
		{
		  "id": "aaav",
		  
			
			"gameBoardTile": {
				"xLocation": "0.0",
				"yLocation": "0.0",
		    "tileMovementType": "GameBoardContinueTile",
		    "gameBoardTileType": "Action"
		  }
		},
		{
		  "id": "aaaw",
		  
			
			"gameBoardTile": {
				"xLocation": "0.0",
				"yLocation": "0.0",
		    "tileMovementType": "GameBoardContinueTile",
		    "gameBoardTileType": "House"
		  }
		},
		{
		  "id": "aaax",
		  
			
			"gameBoardTile": {
				"xLocation": "0.0",
				"yLocation": "0.0",
		    "tileMovementType": "GameBoardContinueTile",
		    "gameBoardTileType": "Action"
		  }
		},
		{
		  "id": "aaay",
		  
			
			"gameBoardTile": {
				"xLocation": "0.0",
				"yLocation": "0.0",
		    "tileMovementType": "GameBoardContinueTile",
		    "gameBoardTileType": "Payday"
		  }
		},
		{
		  "id": "aaaz",
		  
			
			"gameBoardTile": {
				"xLocation": "0.0",
				"yLocation": "0.0",
		    "tileMovementType": "GameBoardContinueTile",
		    "gameBoardTileType": "Action"
		  }
		},
		{
		  "id": "aaaaa",
		  
			
			"gameBoardTile": {
				"xLocation": "0.0",
				"yLocation": "0.0",
		    "tileMovementType": "GameBoardContinueTile",
		    "gameBoardTileType": "Action"
		  }
		},
		{
		  "id": "aaaab",
		  
			
			"gameBoardTile": {
				"xLocation": "0.0",
				"yLocation": "0.0",
		    "tileMovementType": "GameBoardContinueTile",
		    "gameBoardTileType": "Action"
		  }
		},
		{
		  "id": "aaaac",
		  
			
			"gameBoardTile": {
				"xLocation": "0.0",
				"yLocation": "0.0",
		    "tileMovementType": "GameBoardContinueTile",
		    "gameBoardTileType": "Action"
		  }
		},
		{
		  "id": "aaaad",
		  
			
			"gameBoardTile": {
				"xLocation": "0.0",
				"yLocation": "0.0",
		    "tileMovementType": "GameBoardContinueTile",
		    "gameBoardTileType": "Action"
		  }
		},
		{
		  "id": "aaaae",
		  
			
			"gameBoardTile": {
				"xLocation": "0.0",
				"yLocation": "0.0",
		    "tileMovementType": "GameBoardContinueTile",
		    "gameBoardTileType": "Holiday"
		  }
		},
		{
		  "id": "aaaaf",
		  
			
			"gameBoardTile": {
				"xLocation": "0.0",
				"yLocation": "0.0",
		    "tileMovementType": "GameBoardContinueTile",
		    "gameBoardTileType": "Action"
		  }
		},
		{
		  "id": "aaaag",
		  
			
			"gameBoardTile": {
				"xLocation": "0.0",
				"yLocation": "0.0",
		    "tileMovementType": "GameBoardContinueTile",
		    "gameBoardTileType": "Action"
		  }
		},
		{
		  "id": "aaaah",
		  
			
			"gameBoardTile": {
				"xLocation": "0.0",
				"yLocation": "0.0",
		    "tileMovementType": "GameBoardContinueTile",
		    "gameBoardTileType": "Payday"
		  }
		},
		{
		  "id": "aaaai",
		  
			
			"gameBoardTile": {
				"xLocation": "0.0",
				"yLocation": "0.0",
		    "tileMovementType": "GameBoardContinueTile",
		    "gameBoardTileType": "Action"
		  }
		},
		{
		  "id": "aaaaj",
		  
			
			"gameBoardTile": {
				"xLocation": "0.0",
				"yLocation": "0.0",
		    "tileMovementType": "GameBoardContinueTile",
		    "gameBoardTileType": "SpinToWin"
		  }
		},
		{
		  "id": "aaaak",
		  
			
			"gameBoardTile": {
				"xLocation": "0.0",
				"yLocation": "0.0",
		    "tileMovementType": "GameBoardContinueTile",
		    "gameBoardTileType": "Action"
		  }
		},
		{
		  "id": "aaaal",
		  
			
			"gameBoardTile": {
				"xLocation": "0.0",
				"yLocation": "0.0",
		    "tileMovementType": "GameBoardContinueTile",
		    "gameBoardTileType": "Action"
		  }
		},
		{
		  "id": "aaaam",
		  
			
			"gameBoardTile": {
				"xLocation": "0.0",
				"yLocation": "0.0",
		    "tileMovementType": "GameBoardContinueTile",
		    "gameBoardTileType": "House"
		  }
		},
		{
		  "id": "aaaan",
		  
			
			"gameBoardTile": {
				"xLocation": "0.0",
				"yLocation": "0.0",
		    "tileMovementType": "GameBoardContinueTile",
		    "gameBoardTileType": "Payday"
		  }
		},
		{
		  "id": "aaaao",
		  
			
			"gameBoardTile": {
				"xLocation": "0.0",
				"yLocation": "0.0",
		    "tileMovementType": "GameBoardContinueTile",
		    "gameBoardTileType": "Action"
		  }
		},
		{
		  "id": "aaaap",
		  
			
			"gameBoardTile": {
				"xLocation": "0.0",
				"yLocation": "0.0",
		    "tileMovementType": "GameBoardContinueTile",
		    "gameBoardTileType": "Action"
		  }
		},
		{
		  "id": "aaaaq",
		  
			
			"gameBoardTile": {
				"xLocation": "0.0",
				"yLocation": "0.0",
		    "tileMovementType": "GameBoardContinueTile",
		    "gameBoardTileType": "Action"
		  }
		},
		{
		  "id": "aaaar",
		  
			
			"gameBoardTile": {
				"xLocation": "0.0",
				"yLocation": "0.0",
		    "tileMovementType": "GameBoardContinueTile",
		    "gameBoardTileType": "Action"
		  }
		},
		{
		  "id": "aaaas",
		  
			
			"gameBoardTile": {
				"xLocation": "0.0",
				"yLocation": "0.0",
		    "tileMovementType": "GameBoardContinueTile",
		    "gameBoardTileType": "Action"
		  }
		},
		{
		  "id": "aaaat",
		  
			
			"gameBoardTile": {
				"xLocation": "0.0",
				"yLocation": "0.0",
		    "tileMovementType": "GameBoardContinueTile",
		    "gameBoardTileType": "Action"
		  }
		},
		{
		  "id": "aaaau",
		  
			
			"gameBoardTile": {
				"xLocation": "0.0",
				"yLocation": "0.0",
		    "tileMovementType": "GameBoardContinueTile",
		    "gameBoardTileType": "SpinToWin"
		  }
		},
		{
		  "id": "aaaav",
		  
			
			"gameBoardTile": {
				"xLocation": "0.0",
				"yLocation": "0.0",
		    "tileMovementType": "GameBoardContinueTile",
		    "gameBoardTileType": "Action"
		  }
		},
		{
		  "id": "aaaaw",
		  
			
			"gameBoardTile": {
				"xLocation": "0.9",
				"yLocation": "0.9",
		    "tileMovementType": "GameBoardStopTile",
		    "gameBoardTileType": "Stop",
			"gameBoardStopTileType": "Retire"
		  }
		}
	],
	"edges": [{
		"source": "a",
		"target": "b"
	},
	{
		"source": "a",
		"target": "f"
	},
	{
		"source": "b",
		"target": "c"
	},
	{
		"source": "c",
		"target": "d"
	},
	{
		"source": "d",
		"target": "e"
	},
	{
		"source": "f",
		"target": "g"
	},
	{
		"source": "g",
		"target": "h"
	},
	{
		"source": "h",
		"target": "i"
	},
	{
		"source": "i",
		"target": "j"
	},
	{
		"source": "j",
		"target": "k"
	},
	{
		"source": "k",
		"target": "l"
	},
	{
		"source": "l",
		"target": "m"
	},
	{
		"source": "m",
		"target": "n"
	},
	{
		"source": "n",
		"target": "o"
	},
	{
		"source": "o",
		"target": "p"
	},
	{
		"source": "p",
		"target": "q"
	},
	{
		"source": "q",
		"target": "r"
	},
	{
		"source": "r",
		"target": "s"
	},
	{
		"source": "s",
		"target": "t"
	},
	{
		"source": "e",
		"target": "t"
	},
	{
		"source": "t",
		"target": "u"
	},
	{
		"source": "u",
		"target": "v"
	},
	{
		"source": "v",
		"target": "w"
	},
	{
		"source": "w",
		"target": "x"
	},
	{
		"source": "x",
		"target": "y"
	},
	{
		"source": "y",
		"target": "z"
	},
	{
		"source": "z",
		"target": "aa"
	},
	{
		"source": "aa",
		"target": "ab"
	},
	{
		"source": "ab",
		"target": "ac"
	},
    {
      "source": "ac",
      "target": "ad"
    },
	{
      "source": "ad",
      "target": "ae"
    },
	{
      "source": "ae",
      "target": "af"
    },
	{
      "source": "af",
      "target": "ag"
    },
	{
      "source": "ag",
      "target": "ah"
    },
	{
      "source": "ah",
      "target": "ai"
    },
	{
      "source": "ai",
      "target": "aj"
    },
	{
      "source": "aj",
      "target": "ak"
    },
	{
      "source": "ak",
      "target": "al"
    },
	{
      "source": "al",
      "target": "am"
    },
	{
      "source": "am",
      "target": "an"
    },
	{
      "source": "an",
      "target": "ao"
    },
	{
      "source": "ao",
      "target": "ap"
    },
	{
      "source": "ap",
      "target": "aq"
    },
	{
      "source": "aq",
      "target": "ar"
    },
	{
      "source": "ar",
      "target": "as"
    },
	{
      "source": "as",
      "target": "at"
    },
	{
      "source": "at",
      "target": "au"
    },
	{
      "source": "an",
      "target": "av"
    },
	{
      "source": "av",
      "target": "aw"
    },
	{
      "source": "aw",
      "target": "ax"
    },
	{
      "source": "ax",
      "target": "ay"
    },
	{
      "source": "ay",
      "target": "az"
    },
	{
      "source": "az",
      "target": "aaa"
    },
	{
      "source": "aaa",
      "target": "aab"
    },
	{
      "source": "aab",
      "target": "aac"
    },
	{
      "source": "aac",
      "target": "aad"
    },
	{
      "source": "aad",
      "target": "au"
    },
	{
      "source": "au",
      "target": "aae"
    },
	{
      "source": "aae",
      "target": "aaf"
    },
	{
      "source": "aaf",
      "target": "aag"
    },
	{
      "source": "aag",
      "target": "aah"
    },
	{
      "source": "aah",
      "target": "aai"
    },
	{
      "source": "aai",
      "target": "aaj"
    },
	{
      "source": "aaj",
      "target": "aak"
    },
	{
      "source": "aak",
      "target": "aal"
    },
	{
      "source": "aal",
      "target": "aam"
    },
	{
      "source": "aam",
      "target": "aan"
    },
	{
      "source": "aan",
      "target": "aao"
    },
	{
      "source": "aao",
      "target": "aap"
    },
	{
      "source": "aap",
      "target": "aaq"
    },
	{
      "source": "aaq",
      "target": "aar"
    },
	{
      "source": "aar",
      "target": "aas"
    },
	{
      "source": "aas",
      "target": "aat"
    },
	{
      "source": "aat",
      "target": "aau"
    },
	{
      "source": "aau",
      "target": "aav"
    },
	{
      "source": "aav",
      "target": "aaw"
    },
	{
      "source": "aaw",
      "target": "aax"
    },
	{
      "source": "aax",
      "target": "aay"
    },
	{
      "source": "aaq",
      "target": "aaz"
    },
	{
      "source": "aaz",
      "target": "aaaa"
    },
	{
      "source": "aaaa",
      "target": "aaab"
    },
	{
      "source": "aaab",
      "target": "aaac"
    },
	{
      "source": "aaac",
      "target": "aaad"
    },
	{
      "source": "aaad",
      "target": "aaae"
    },
	{
      "source": "aaae",
      "target": "aaaf"
    },
	{
      "source": "aaaf",
      "target": "aaag"
    },
	{
      "source": "aaag",
      "target": "aaah"
    },
	{
      "source": "aaah",
      "target": "aay"
    },
	{
      "source": "aay",
      "target": "aaai"
    },
	{
      "source": "aaai",
      "target": "aaaj"
    },
	{
      "source": "aaaj",
      "target": "aaak"
    },
	{
      "source": "aaak",
      "target": "aaal"
    },
	{
      "source": "aaal",
      "target": "aaam"
    },
	{
      "source": "aaam",
      "target": "aaan"
    },
	{
      "source": "aaan",
      "target": "aaao"
    },
	{
      "source": "aaao",
      "target": "aaap"
    },
	{
      "source": "aaap",
      "target": "aaaq"
    },
	{
      "source": "aaaq",
      "target": "aaar"
    },
	{
      "source": "aaar",
      "target": "aaas"
    },
	{
      "source": "aaas",
      "target": "aaat"
    },
	{
      "source": "aaat",
      "target": "aaau"
    },
	{
      "source": "aaau",
      "target": "aaav"
    },
	{
      "source": "aaav",
      "target": "aaaw"
    },
	{
      "source": "aaaw",
      "target": "aaax"
    },
	{
      "source": "aaax",
      "target": "aaay"
    },
	{
      "source": "aaay",
      "target": "aaaz"
    },
	{
      "source": "aaaz",
      "target": "aaaaa"
    },
	{
      "source": "aaaaa",
      "target": "aaaab"
    },
	{
      "source": "aaaab",
      "target": "aaaac"
    },
	{
      "source": "aaaac",
      "target": "aaaad"
    },
	{
      "source": "aaaad",
      "target": "aaaae"
    },
	{
      "source": "aaaae",
      "target": "aaaaf"
    },
	{
      "source": "aaaaf",
      "target": "aaaag"
    },
	{
      "source": "aaaag",
      "target": "aaaah"
    },
	{
      "source": "aaaah",
      "target": "aaaai"
    },
	{
      "source": "aaaai",
      "target": "aaaaj"
    },
	{
      "source": "aaaaj",
      "target": "aaaak"
    },
	{
      "source": "aaaak",
      "target": "aaaal"
    },
	{
      "source": "aaaal",
      "target": "aaaam"
    },
	{
      "source": "aaaam",
      "target": "aaaan"
    },
	{
      "source": "aaaan",
      "target": "aaaao"
    },
	{
      "source": "aaaao",
      "target": "aaaap"
    },
	{
      "source": "aaaap",
      "target": "aaaaq"
    },
	{
      "source": "aaaaq",
      "target": "aaaar"
    },
	{
      "source": "aaaar",
      "target": "aaaas"
    },
	{
      "source": "aaaas",
      "target": "aaaat"
    },
	{
      "source": "aaaat",
      "target": "aaaau"
    },
	{
      "source": "aaaau",
      "target": "aaaav"
    },
	{
      "source": "aaaav",
      "target": "aaaaw"
    }
	]
}